shift4/__init__.py
shift4/__version__.py
shift4/blacklist.py
shift4/cards.py
shift4/charges.py
shift4/checkout_request.py
shift4/credits.py
shift4/customers.py
shift4/disputes.py
shift4/events.py
shift4/exception.py
shift4/file_uploads.py
shift4/fraud_warnings.py
shift4/payment_methods.py
shift4/plans.py
shift4/request_options.py
shift4/resource.py
shift4/subscriptions.py
shift4/tokens.py
shift4-2.1.0.dist-info/LICENSE
shift4-2.1.0.dist-info/METADATA
shift4-2.1.0.dist-info/WHEEL
shift4-2.1.0.dist-info/top_level.txt
shift4-2.1.0.dist-info/RECORD
