Metadata-Version: 2.1
Name: shift4
Version: 2.1.0
Summary: Shift4 Python Library
Home-page: https://github.com/shift4developer/shift4-python
Author: Shift4
Author-email: devsupport@shift4.com
License: MIT
Keywords: payment
Classifier: Development Status :: 5 - Production/Stable
Classifier: Intended Audience :: Developers
Classifier: Topic :: Software Development :: Build Tools
Classifier: License :: OSI Approved :: MIT License
Classifier: Programming Language :: Python :: 3.7
Classifier: Programming Language :: Python :: 3.8
Classifier: Programming Language :: Python :: 3.9
Classifier: Programming Language :: Python :: 3.10
Classifier: Programming Language :: Python :: 3.11
License-File: LICENSE
Requires-Dist: requests >=2.27.1
